<PossibleSpawnBlocks xmlns:xsd="http://www.w3.org/2001/XMLSchema" xmlns:xsi="http://www.w3.org/2001/XMLSchema-instance">
  <CarGeneratorBlock>
    <CarGeneratorBlock>
      <Position>
        <X>407.7554</X>
        <Y>-984.2084</Y>
        <Z>29.89806</Z>
      </Position>
      <Distance>2</Distance>
      <DebugName>MissionRowPolice</DebugName>
    </CarGeneratorBlock>
    <CarGeneratorBlock>
      <Position>
        <X>408.0923</X>
        <Y>-988.8488</Y>
        <Z>29.85523</Z>
      </Position>
      <Distance>2</Distance>
      <DebugName>MissionRowPolice</DebugName>
    </CarGeneratorBlock>
    <CarGeneratorBlock>
      <Position>
        <X>407.9883</X>
        <Y>-998.3094</Y>
        <Z>29.81112</Z>
      </Position>
      <Distance>2</Distance>
      <DebugName>MissionRowPolice</DebugName>
    </CarGeneratorBlock>
    <CarGeneratorBlock>
      <Position>
        <X>427.5909</X>
        <Y>-1027.707</Y>
        <Z>29.22805</Z>
      </Position>
      <Distance>2</Distance>
      <DebugName>MissionRowPolice</DebugName>
    </CarGeneratorBlock>
    <CarGeneratorBlock>
      <Position>
        <X>434.9848</X>
        <Y>-1027.103</Y>
        <Z>29.12844</Z>
      </Position>
      <Distance>2</Distance>
      <DebugName>MissionRowPolice</DebugName>
    </CarGeneratorBlock>
    <CarGeneratorBlock>
      <Position>
        <X>442.5143</X>
        <Y>-1026.687</Y>
        <Z>28.98147</Z>
      </Position>
      <Distance>2</Distance>
      <DebugName>MissionRowPolice</DebugName>
    </CarGeneratorBlock>
    <CarGeneratorBlock>
      <Position>
        <X>446.3985</X>
        <Y>-1026.087</Y>
        <Z>28.92508</Z>
      </Position>
      <Distance>2</Distance>
      <DebugName>MissionRowPolice</DebugName>
    </CarGeneratorBlock>
    <CarGeneratorBlock>
      <Position>
        <X>496.3687</X>
        <Y>-996.015</Y>
        <Z>28.3387</Z>
      </Position>
      <Distance>2</Distance>
      <DebugName>MissionRowPolice</DebugName>
    </CarGeneratorBlock>
    <CarGeneratorBlock>
      <Position>
        <X>496.3721</X>
        <Y>-1016.798</Y>
        <Z>28.687</Z>
      </Position>
      <Distance>2</Distance>
      <DebugName>MissionRowPolice</DebugName>
    </CarGeneratorBlock>
    <CarGeneratorBlock>
      <Position>
        <X>388.9854</X>
        <Y>-1612.977</Y>
        <Z>29.21355</Z>
      </Position>
      <Distance>2</Distance>
      <DebugName>DavisPolice</DebugName>
    </CarGeneratorBlock>
    <CarGeneratorBlock>
      <Position>
        <X>392.7548</X>
        <Y>-1608.376</Y>
        <Z>29.21355</Z>
      </Position>
      <Distance>2</Distance>
      <DebugName>DavisPolice</DebugName>
    </CarGeneratorBlock>
    <CarGeneratorBlock>
      <Position>
        <X>399.393</X>
        <Y>-1621.396</Y>
        <Z>29.20119</Z>
      </Position>
      <Distance>2</Distance>
      <DebugName>DavisPolice</DebugName>
    </CarGeneratorBlock>
    <CarGeneratorBlock>
      <Position>
        <X>351.3006</X>
        <Y>-1556.711</Y>
        <Z>29.24393</Z>
      </Position>
      <Distance>2</Distance>
      <DebugName>DavisPolice</DebugName>
    </CarGeneratorBlock>
    <CarGeneratorBlock>
      <Position>
        <X>-1625.343</X>
        <Y>-1013.629</Y>
        <Z>13.89048</Z>
      </Position>
      <Distance>2</Distance>
      <DebugName>DelPerroPierPolice</DebugName>
    </CarGeneratorBlock>
    <CarGeneratorBlock>
      <Position>
        <X>-1072.822</X>
        <Y>-880.3561</Y>
        <Z>4.809089</Z>
      </Position>
      <Distance>2</Distance>
      <DebugName>VespucciPolice</DebugName>
    </CarGeneratorBlock>
    <CarGeneratorBlock>
      <Position>
        <X>-1075.95</X>
        <Y>-882.3492</Y>
        <Z>4.809089</Z>
      </Position>
      <Distance>2</Distance>
      <DebugName>VespucciPolice</DebugName>
    </CarGeneratorBlock>
    <CarGeneratorBlock>
      <Position>
        <X>-1051.726</X>
        <Y>-867.1277</Y>
        <Z>4.809089</Z>
      </Position>
      <Distance>2</Distance>
      <DebugName>VespucciPolice</DebugName>
    </CarGeneratorBlock>
    <CarGeneratorBlock>
      <Position>
        <X>-1045.53</X>
        <Y>-861.5321</Y>
        <Z>4.809089</Z>
      </Position>
      <Distance>2</Distance>
      <DebugName>VespucciPolice</DebugName>
    </CarGeneratorBlock>
    <CarGeneratorBlock>
      <Position>
        <X>-1042.226</X>
        <Y>-857.9979</Y>
        <Z>4.809089</Z>
      </Position>
      <Distance>2</Distance>
      <DebugName>VespucciPolice</DebugName>
    </CarGeneratorBlock>
    <CarGeneratorBlock>
      <Position>
        <X>-1047.814</X>
        <Y>-846.7044</Y>
        <Z>4.809089</Z>
      </Position>
      <Distance>2</Distance>
      <DebugName>VespucciPolice</DebugName>
    </CarGeneratorBlock>
    <CarGeneratorBlock>
      <Position>
        <X>-1052.352</X>
        <Y>-846.8544</Y>
        <Z>4.809089</Z>
      </Position>
      <Distance>2</Distance>
      <DebugName>VespucciPolice</DebugName>
    </CarGeneratorBlock>
    <CarGeneratorBlock>
      <Position>
        <X>-1055.076</X>
        <Y>-849.5068</Y>
        <Z>4.809089</Z>
      </Position>
      <Distance>2</Distance>
      <DebugName>VespucciPolice</DebugName>
    </CarGeneratorBlock>
    <CarGeneratorBlock>
      <Position>
        <X>-1058.752</X>
        <Y>-851.4465</Y>
        <Z>4.809089</Z>
      </Position>
      <Distance>2</Distance>
      <DebugName>VespucciPolice</DebugName>
    </CarGeneratorBlock>
    <CarGeneratorBlock>
      <Position>
        <X>-1126.5</X>
        <Y>-864.8307</Y>
        <Z>13.63185</Z>
      </Position>
      <Distance>2</Distance>
      <DebugName>VespucciPolice</DebugName>
    </CarGeneratorBlock>
    <CarGeneratorBlock>
      <Position>
        <X>-1122.896</X>
        <Y>-863.4746</Y>
        <Z>13.6122</Z>
      </Position>
      <Distance>2</Distance>
      <DebugName>VespucciPolice</DebugName>
    </CarGeneratorBlock>
    <CarGeneratorBlock>
      <Position>
        <X>-1115.937</X>
        <Y>-857.7859</Y>
        <Z>13.65187</Z>
      </Position>
      <Distance>2</Distance>
      <DebugName>VespucciPolice</DebugName>
    </CarGeneratorBlock>
    <CarGeneratorBlock>
      <Position>
        <X>-1138.613</X>
        <Y>-845.7916</Y>
        <Z>13.98058</Z>
      </Position>
      <Distance>2</Distance>
      <DebugName>VespucciPolice</DebugName>
    </CarGeneratorBlock>
    <CarGeneratorBlock>
      <Position>
        <X>-574.256</X>
        <Y>-168.7862</Y>
        <Z>38.49216</Z>
      </Position>
      <Distance>2</Distance>
      <DebugName>RichmanPolice</DebugName>
    </CarGeneratorBlock>
    <CarGeneratorBlock>
      <Position>
        <X>-557.7739</X>
        <Y>-161.9565</Y>
        <Z>38.62593</Z>
      </Position>
      <Distance>2</Distance>
      <DebugName>RichmanPolice</DebugName>
    </CarGeneratorBlock>
    <CarGeneratorBlock>
      <Position>
        <X>-559.7783</X>
        <Y>-147.1107</Y>
        <Z>38.65532</Z>
      </Position>
      <Distance>2</Distance>
      <DebugName>RichmanPolice</DebugName>
    </CarGeneratorBlock>
    <CarGeneratorBlock>
      <Position>
        <X>-555.6528</X>
        <Y>-145.4567</Y>
        <Z>38.72502</Z>
      </Position>
      <Distance>2</Distance>
      <DebugName>RichmanPolice</DebugName>
    </CarGeneratorBlock>
    <CarGeneratorBlock>
      <Position>
        <X>-551.0397</X>
        <Y>-144.0132</Y>
        <Z>38.65663</Z>
      </Position>
      <Distance>2</Distance>
      <DebugName>RichmanPolice</DebugName>
    </CarGeneratorBlock>
    <CarGeneratorBlock>
      <Position>
        <X>-454.4307</X>
        <Y>6040.472</Y>
        <Z>31.17424</Z>
      </Position>
      <Distance>2</Distance>
      <DebugName>PaletoPolice</DebugName>
    </CarGeneratorBlock>
    <CarGeneratorBlock>
      <Position>
        <X>-457.8087</X>
        <Y>6043.849</Y>
        <Z>31.17424</Z>
      </Position>
      <Distance>2</Distance>
      <DebugName>PaletoPolice</DebugName>
    </CarGeneratorBlock>
    <CarGeneratorBlock>
      <Position>
        <X>-468.1928</X>
        <Y>6038.506</Y>
        <Z>31.17422</Z>
      </Position>
      <Distance>2</Distance>
      <DebugName>PaletoPolice</DebugName>
    </CarGeneratorBlock>
    <CarGeneratorBlock>
      <Position>
        <X>-475.1396</X>
        <Y>6031.421</Y>
        <Z>31.17419</Z>
      </Position>
      <Distance>2</Distance>
      <DebugName>PaletoPolice</DebugName>
    </CarGeneratorBlock>
    <CarGeneratorBlock>
      <Position>
        <X>-458.788</X>
        <Y>6005.529</Y>
        <Z>31.17422</Z>
      </Position>
      <Distance>2</Distance>
      <DebugName>PaletoPolice</DebugName>
    </CarGeneratorBlock>
    <CarGeneratorBlock>
      <Position>
        <X>-455.154</X>
        <Y>6001.894</Y>
        <Z>31.17422</Z>
      </Position>
      <Distance>2</Distance>
      <DebugName>PaletoPolice</DebugName>
    </CarGeneratorBlock>
    <CarGeneratorBlock>
      <Position>
        <X>1831.629</X>
        <Y>3662.91</Y>
        <Z>33.92607</Z>
      </Position>
      <Distance>2</Distance>
      <DebugName>SandyPolice</DebugName>
    </CarGeneratorBlock>
    <CarGeneratorBlock>
      <Position>
        <X>1835.127</X>
        <Y>3664.892</Y>
        <Z>33.92607</Z>
      </Position>
      <Distance>2</Distance>
      <DebugName>SandyPolice</DebugName>
    </CarGeneratorBlock>
    <CarGeneratorBlock>
      <Position>
        <X>1847.131</X>
        <Y>3672.587</Y>
        <Z>33.92607</Z>
      </Position>
      <Distance>2</Distance>
      <DebugName>SandyPolice</DebugName>
    </CarGeneratorBlock>
    <CarGeneratorBlock>
      <Position>
        <X>666.4646</X>
        <Y>-11.79645</Y>
        <Z>82.76681</Z>
      </Position>
      <Distance>2</Distance>
      <DebugName>VinewoodPolice</DebugName>
    </CarGeneratorBlock>
    <CarGeneratorBlock>
      <Position>
        <X>621.6934</X>
        <Y>26.27448</Y>
        <Z>88.66011</Z>
      </Position>
      <Distance>2</Distance>
      <DebugName>VinewoodPolice</DebugName>
    </CarGeneratorBlock>
    <CarGeneratorBlock>
      <Position>
        <X>615.3292</X>
        <Y>28.48364</Y>
        <Z>89.28476</Z>
      </Position>
      <Distance>2</Distance>
      <DebugName>VinewoodPolice</DebugName>
    </CarGeneratorBlock>
    <CarGeneratorBlock>
      <Position>
        <X>609.7616</X>
        <Y>30.84756</Y>
        <Z>89.91243</Z>
      </Position>
      <Distance>2</Distance>
      <DebugName>VinewoodPolice</DebugName>
    </CarGeneratorBlock>
    <CarGeneratorBlock>
      <Position>
        <X>597.8726</X>
        <Y>34.8121</Y>
        <Z>91.07567</Z>
      </Position>
      <Distance>2</Distance>
      <DebugName>VinewoodPolice</DebugName>
    </CarGeneratorBlock>
    <CarGeneratorBlock>
      <Position>
        <X>586.7384</X>
        <Y>37.78894</Y>
        <Z>92.30818</Z>
      </Position>
      <Distance>2</Distance>
      <DebugName>VinewoodPolice</DebugName>
    </CarGeneratorBlock>
    <CarGeneratorBlock>
      <Position>
        <X>580.8351</X>
        <Y>38.85468</Y>
        <Z>92.82274</Z>
      </Position>
      <Distance>2</Distance>
      <DebugName>VinewoodPolice</DebugName>
    </CarGeneratorBlock>
    <CarGeneratorBlock>
      <Position>
        <X>822.8635</X>
        <Y>-1258.039</Y>
        <Z>26.34347</Z>
      </Position>
      <Distance>2</Distance>
      <DebugName>LaMesaPolice</DebugName>
    </CarGeneratorBlock>
    <CarGeneratorBlock>
      <Position>
        <X>828.0373</X>
        <Y>-1258.039</Y>
        <Z>26.34347</Z>
      </Position>
      <Distance>2</Distance>
      <DebugName>LaMesaPolice</DebugName>
    </CarGeneratorBlock>
    <CarGeneratorBlock>
      <Position>
        <X>833.577</X>
        <Y>-1258.954</Y>
        <Z>26.34347</Z>
      </Position>
      <Distance>2</Distance>
      <DebugName>LaMesaPolice</DebugName>
    </CarGeneratorBlock>
    <CarGeneratorBlock>
      <Position>
        <X>838.7137</X>
        <Y>-1271.55</Y>
        <Z>26.34347</Z>
      </Position>
      <Distance>2</Distance>
      <DebugName>LaMesaPolice</DebugName>
    </CarGeneratorBlock>
    <CarGeneratorBlock>
      <Position>
        <X>833.4279</X>
        <Y>-1271.55</Y>
        <Z>26.34347</Z>
      </Position>
      <Distance>2</Distance>
      <DebugName>LaMesaPolice</DebugName>
    </CarGeneratorBlock>
    <CarGeneratorBlock>
      <Position>
        <X>822.5837</X>
        <Y>-1271.55</Y>
        <Z>26.34347</Z>
      </Position>
      <Distance>2</Distance>
      <DebugName>LaMesaPolice</DebugName>
    </CarGeneratorBlock>
    <CarGeneratorBlock>
      <Position>
        <X>828.1719</X>
        <Y>-1333.792</Y>
        <Z>26.18776</Z>
      </Position>
      <Distance>2</Distance>
      <DebugName>LaMesaPolice</DebugName>
    </CarGeneratorBlock>
    <CarGeneratorBlock>
      <Position>
        <X>828.1719</X>
        <Y>-1339.649</Y>
        <Z>26.18776</Z>
      </Position>
      <Distance>2</Distance>
      <DebugName>LaMesaPolice</DebugName>
    </CarGeneratorBlock>
    <CarGeneratorBlock>
      <Position>
        <X>828.1719</X>
        <Y>-1345.815</Y>
        <Z>26.18776</Z>
      </Position>
      <Distance>2</Distance>
      <DebugName>LaMesaPolice</DebugName>
    </CarGeneratorBlock>
    <CarGeneratorBlock>
      <Position>
        <X>828.362</X>
        <Y>-1351.482</Y>
        <Z>26.21234</Z>
      </Position>
      <Distance>2</Distance>
      <DebugName>LaMesaPolice</DebugName>
    </CarGeneratorBlock>
    <CarGeneratorBlock>
      <Position>
        <X>843.9627</X>
        <Y>-1334.354</Y>
        <Z>26.17253</Z>
      </Position>
      <Distance>2</Distance>
      <DebugName>LaMesaPolice</DebugName>
    </CarGeneratorBlock>
    <CarGeneratorBlock>
      <Position>
        <X>843.874</X>
        <Y>-1340.518</Y>
        <Z>26.18776</Z>
      </Position>
      <Distance>2</Distance>
      <DebugName>LaMesaPolice</DebugName>
    </CarGeneratorBlock>
    <CarGeneratorBlock>
      <Position>
        <X>844.3544</X>
        <Y>-1346.3</Y>
        <Z>26.21234</Z>
      </Position>
      <Distance>2</Distance>
      <DebugName>LaMesaPolice</DebugName>
    </CarGeneratorBlock>
    <CarGeneratorBlock>
      <Position>
        <X>843.7897</X>
        <Y>-1352.283</Y>
        <Z>26.21234</Z>
      </Position>
      <Distance>2</Distance>
      <DebugName>LaMesaPolice</DebugName>
    </CarGeneratorBlock>
    <CarGeneratorBlock>
      <Position>
        <X>865.7624</X>
        <Y>-1378.407</Y>
        <Z>26.21234</Z>
      </Position>
      <Distance>2</Distance>
      <DebugName>LaMesaPolice</DebugName>
    </CarGeneratorBlock>
    <CarGeneratorBlock>
      <Position>
        <X>862.8425</X>
        <Y>-1383.55</Y>
        <Z>26.21234</Z>
      </Position>
      <Distance>2</Distance>
      <DebugName>LaMesaPolice</DebugName>
    </CarGeneratorBlock>
    <CarGeneratorBlock>
      <Position>
        <X>859.8381</X>
        <Y>-1388.58</Y>
        <Z>26.21234</Z>
      </Position>
      <Distance>2</Distance>
      <DebugName>LaMesaPolice</DebugName>
    </CarGeneratorBlock>
    <CarGeneratorBlock>
      <Position>
        <X>857.2202</X>
        <Y>-1393.802</Y>
        <Z>26.21234</Z>
      </Position>
      <Distance>2</Distance>
      <DebugName>LaMesaPolice</DebugName>
    </CarGeneratorBlock>
    <CarGeneratorBlock>
      <Position>
        <X>854.2248</X>
        <Y>-1398.952</Y>
        <Z>26.21234</Z>
      </Position>
      <Distance>2</Distance>
      <DebugName>LaMesaPolice</DebugName>
    </CarGeneratorBlock>
    <CarGeneratorBlock>
      <Position>
        <X>1855.314</X>
        <Y>2578.854</Y>
        <Z>46.42464</Z>
      </Position>
      <Distance>2</Distance>
      <DebugName>BoilingbrokePrison</DebugName>
    </CarGeneratorBlock>
    <CarGeneratorBlock>
      <Position>
        <X>1799.826</X>
        <Y>2600.908</Y>
        <Z>45.58898</Z>
      </Position>
      <Distance>2</Distance>
      <DebugName>BoilingbrokePrison</DebugName>
    </CarGeneratorBlock>
    <CarGeneratorBlock>
      <Position>
        <X>-178.2882</X>
        <Y>-1607.417</Y>
        <Z>33.43019</Z>
      </Position>
      <Distance>2</Distance>
      <DebugName>familesgang1</DebugName>
    </CarGeneratorBlock>
  </CarGeneratorBlock>
  <ScenarioBlocks>
    <ScenarioBlock>
      <Position>
        <X>838.9286</X>
        <Y>-1259.166</Y>
        <Z>25.38143</Z>
      </Position>
      <Distance>2</Distance>
      <DebugName>GeneralPolice</DebugName>
    </ScenarioBlock>
    <ScenarioBlock>
      <Position>
        <X>837.0612</X>
        <Y>-1257.972</Y>
        <Z>25.36833</Z>
      </Position>
      <Distance>2</Distance>
      <DebugName>GeneralPolice</DebugName>
    </ScenarioBlock>
    <ScenarioBlock>
      <Position>
        <X>824.9189</X>
        <Y>-1263.116</Y>
        <Z>25.26017</Z>
      </Position>
      <Distance>2</Distance>
      <DebugName>GeneralPolice</DebugName>
    </ScenarioBlock>
    <ScenarioBlock>
      <Position>
        <X>455.6195</X>
        <Y>-1026.146</Y>
        <Z>27.47295</Z>
      </Position>
      <Distance>2</Distance>
      <DebugName>GeneralPolice</DebugName>
    </ScenarioBlock>
    <ScenarioBlock>
      <Position>
        <X>438.6183</X>
        <Y>-1026.667</Y>
        <Z>27.7867</Z>
      </Position>
      <Distance>2</Distance>
      <DebugName>GeneralPolice</DebugName>
    </ScenarioBlock>
    <ScenarioBlock>
      <Position>
        <X>407.7591</X>
        <Y>-1005.385</Y>
        <Z>28.26613</Z>
      </Position>
      <Distance>2</Distance>
      <DebugName>GeneralPolice</DebugName>
    </ScenarioBlock>
    <ScenarioBlock>
      <Position>
        <X>407.9486</X>
        <Y>-1008.231</Y>
        <Z>28.26636</Z>
      </Position>
      <Distance>2</Distance>
      <DebugName>GeneralPolice</DebugName>
    </ScenarioBlock>
    <ScenarioBlock>
      <Position>
        <X>-562.8094</X>
        <Y>-148.4117</Y>
        <Z>37.01614</Z>
      </Position>
      <Distance>2</Distance>
      <DebugName>GeneralPolice</DebugName>
    </ScenarioBlock>
    <ScenarioBlock>
      <Position>
        <X>-548.7076</X>
        <Y>-141.6616</Y>
        <Z>37.29326</Z>
      </Position>
      <Distance>2</Distance>
      <DebugName>GeneralPolice</DebugName>
    </ScenarioBlock>
    <ScenarioBlock>
      <Position>
        <X>-1039.343</X>
        <Y>-855.5767</Y>
        <Z>3.875723</Z>
      </Position>
      <Distance>2</Distance>
      <DebugName>GeneralPolice</DebugName>
    </ScenarioBlock>
    <ScenarioBlock>
      <Position>
        <X>-1048.334</X>
        <Y>-864.5882</Y>
        <Z>3.992599</Z>
      </Position>
      <Distance>2</Distance>
      <DebugName>GeneralPolice</DebugName>
    </ScenarioBlock>
    <ScenarioBlock>
      <Position>
        <X>-1069.269</X>
        <Y>-878.6844</Y>
        <Z>3.855752</Z>
      </Position>
      <Distance>2</Distance>
      <DebugName>GeneralPolice</DebugName>
    </ScenarioBlock>
    <ScenarioBlock>
      <Position>
        <X>-1128.474</X>
        <Y>-866.9715</Y>
        <Z>12.51155</Z>
      </Position>
      <Distance>2</Distance>
      <DebugName>GeneralPolice</DebugName>
    </ScenarioBlock>
    <ScenarioBlock>
      <Position>
        <X>-1120.375</X>
        <Y>-858.11</Y>
        <Z>12.52164</Z>
      </Position>
      <Distance>2</Distance>
      <DebugName>GeneralPolice</DebugName>
    </ScenarioBlock>
    <ScenarioBlock>
      <Position>
        <X>-1112.189</X>
        <Y>-855.1146</Y>
        <Z>12.53287</Z>
      </Position>
      <Distance>2</Distance>
      <DebugName>GeneralPolice</DebugName>
    </ScenarioBlock>
    <ScenarioBlock>
      <Position>
        <X>-1125.52</X>
        <Y>-816.9467</Y>
        <Z>14.99161</Z>
      </Position>
      <Distance>2</Distance>
      <DebugName>GeneralPolice</DebugName>
    </ScenarioBlock>
    <ScenarioBlock>
      <Position>
        <X>-1104.038</X>
        <Y>-797.9</Y>
        <Z>17.30989</Z>
      </Position>
      <Distance>2</Distance>
      <DebugName>GeneralPolice</DebugName>
    </ScenarioBlock>
    <ScenarioBlock>
      <Position>
        <X>-1112.705</X>
        <Y>-804.9168</Y>
        <Z>16.46241</Z>
      </Position>
      <Distance>2</Distance>
      <DebugName>GeneralPolice</DebugName>
    </ScenarioBlock>
    <ScenarioBlock>
      <Position>
        <X>1868.631</X>
        <Y>3685.344</Y>
        <Z>32.75556</Z>
      </Position>
      <Distance>2</Distance>
      <DebugName>GeneralPolice</DebugName>
    </ScenarioBlock>
    <ScenarioBlock>
      <Position>
        <X>1866.067</X>
        <Y>3683.386</Y>
        <Z>32.72648</Z>
      </Position>
      <Distance>2</Distance>
      <DebugName>GeneralPolice</DebugName>
    </ScenarioBlock>
    <ScenarioBlock>
      <Position>
        <X>1862.838</X>
        <Y>3682.098</Y>
        <Z>32.71787</Z>
      </Position>
      <Distance>2</Distance>
      <DebugName>GeneralPolice</DebugName>
    </ScenarioBlock>
    <ScenarioBlock>
      <Position>
        <X>1853.62</X>
        <Y>3675.808</Y>
        <Z>32.75896</Z>
      </Position>
      <Distance>2</Distance>
      <DebugName>GeneralPolice</DebugName>
    </ScenarioBlock>
    <ScenarioBlock>
      <Position>
        <X>-482.731</X>
        <Y>6024.876</Y>
        <Z>30.34054</Z>
      </Position>
      <Distance>2</Distance>
      <DebugName>GeneralPolice</DebugName>
    </ScenarioBlock>
    <ScenarioBlock>
      <Position>
        <X>-479.5346</X>
        <Y>6028.117</Y>
        <Z>30.34054</Z>
      </Position>
      <Distance>2</Distance>
      <DebugName>GeneralPolice</DebugName>
    </ScenarioBlock>
    <ScenarioBlock>
      <Position>
        <X>-437.7312</X>
        <Y>6087.632</Y>
        <Z>30.42623</Z>
      </Position>
      <Distance>2</Distance>
      <DebugName>GeneralPolice</DebugName>
    </ScenarioBlock>
    <ScenarioBlock>
      <Position>
        <X>-431.8985</X>
        <Y>6032.511</Y>
        <Z>30.34053</Z>
      </Position>
      <Distance>2</Distance>
      <DebugName>GeneralPolice</DebugName>
    </ScenarioBlock>
    <ScenarioBlock>
      <Position>
        <X>374.2932</X>
        <Y>795.6959</Y>
        <Z>187.5605</Z>
      </Position>
      <Distance>2</Distance>
      <DebugName>RangeStationPolice</DebugName>
    </ScenarioBlock>
    <ScenarioBlock>
      <Position>
        <X>-256.2089</X>
        <Y>-2029.314</Y>
        <Z>28.94582</Z>
      </Position>
      <Distance>2</Distance>
      <DebugName>MazeBankSecurity</DebugName>
    </ScenarioBlock>
    <ScenarioBlock>
      <Position>
        <X>-252.9283</X>
        <Y>-2025.2</Y>
        <Z>28.94582</Z>
      </Position>
      <Distance>2</Distance>
      <DebugName>MazeBankSecurity</DebugName>
    </ScenarioBlock>
    <ScenarioBlock>
      <Position>
        <X>-241.3938</X>
        <Y>-2023.062</Y>
        <Z>28.94582</Z>
      </Position>
      <Distance>2</Distance>
      <DebugName>MazeBankSecurity</DebugName>
    </ScenarioBlock>
    <ScenarioBlock>
      <Position>
        <X>-285.3585</X>
        <Y>-2056.294</Y>
        <Z>28.94583</Z>
      </Position>
      <Distance>2</Distance>
      <DebugName>MazeBankSecurity</DebugName>
    </ScenarioBlock>
    <ScenarioBlock>
      <Position>
        <X>-336.9773</X>
        <Y>-2046.85</Y>
        <Z>28.94642</Z>
      </Position>
      <Distance>2</Distance>
      <DebugName>MazeBankSecurity</DebugName>
    </ScenarioBlock>
    <ScenarioBlock>
      <Position>
        <X>-372.0268</X>
        <Y>-2018.85</Y>
        <Z>28.94642</Z>
      </Position>
      <Distance>2</Distance>
      <DebugName>MazeBankSecurity</DebugName>
    </ScenarioBlock>
    <ScenarioBlock>
      <Position>
        <X>-395.8358</X>
        <Y>-1997.162</Y>
        <Z>28.94642</Z>
      </Position>
      <Distance>2</Distance>
      <DebugName>MazeBankSecurity</DebugName>
    </ScenarioBlock>
    <ScenarioBlock>
      <Position>
        <X>-402.0461</X>
        <Y>-1905.517</Y>
        <Z>28.94614</Z>
      </Position>
      <Distance>2</Distance>
      <DebugName>MazeBankSecurity</DebugName>
    </ScenarioBlock>
    <ScenarioBlock>
      <Position>
        <X>-337.9023</X>
        <Y>-1880.646</Y>
        <Z>28.94614</Z>
      </Position>
      <Distance>2</Distance>
      <DebugName>MazeBankSecurity</DebugName>
    </ScenarioBlock>
    <ScenarioBlock>
      <Position>
        <X>-309.1234</X>
        <Y>-1891.761</Y>
        <Z>28.94639</Z>
      </Position>
      <Distance>2</Distance>
      <DebugName>MazeBankSecurity</DebugName>
    </ScenarioBlock>
    <ScenarioBlock>
      <Position>
        <X>-283.2107</X>
        <Y>-1913.418</Y>
        <Z>28.94639</Z>
      </Position>
      <Distance>2</Distance>
      <DebugName>MazeBankSecurity</DebugName>
    </ScenarioBlock>
    <ScenarioBlock>
      <Position>
        <X>-277.8984</X>
        <Y>-1918.732</Y>
        <Z>28.94639</Z>
      </Position>
      <Distance>2</Distance>
      <DebugName>MazeBankSecurity</DebugName>
    </ScenarioBlock>
    <ScenarioBlock>
      <Position>
        <X>-233.965</X>
        <Y>-1973.487</Y>
        <Z>28.94639</Z>
      </Position>
      <Distance>2</Distance>
      <DebugName>MazeBankSecurity</DebugName>
    </ScenarioBlock>
    <ScenarioBlock>
      <Position>
        <X>-802.0435</X>
        <Y>-225.7791</Y>
        <Z>36.20076</Z>
      </Position>
      <Distance>2</Distance>
      <DebugName>LuxuryAutoSecurity</DebugName>
    </ScenarioBlock>
    <ScenarioBlock>
      <Position>
        <X>1862.066</X>
        <Y>2593.06</Y>
        <Z>45.67203</Z>
      </Position>
      <Distance>50</Distance>
      <DebugName>PrisonMain</DebugName>
    </ScenarioBlock>
    <ScenarioBlock>
      <Position>
        <X>1803.225</X>
        <Y>2623.1</Y>
        <Z>44.5028</Z>
      </Position>
      <Distance>2</Distance>
      <DebugName>PrisonGeneral</DebugName>
    </ScenarioBlock>
    <ScenarioBlock>
      <Position>
        <X>1727.828</X>
        <Y>2439.606</Y>
        <Z>44.56514</Z>
      </Position>
      <Distance>2</Distance>
      <DebugName>PrisonGeneral</DebugName>
    </ScenarioBlock>
    <ScenarioBlock>
      <Position>
        <X>1799.826</X>
        <Y>2600.908</Y>
        <Z>45.58898</Z>
      </Position>
      <Distance>2</Distance>
      <DebugName>PrisonGeneral</DebugName>
    </ScenarioBlock>
    <ScenarioBlock>
      <Position>
        <X>1803.225</X>
        <Y>2623.1</Y>
        <Z>44.5028</Z>
      </Position>
      <Distance>2</Distance>
      <DebugName>PrisonGeneral</DebugName>
    </ScenarioBlock>
    <ScenarioBlock>
      <Position>
        <X>1784.646</X>
        <Y>2626.016</Y>
        <Z>44.56556</Z>
      </Position>
      <Distance>2</Distance>
      <DebugName>PrisonGeneral</DebugName>
    </ScenarioBlock>
    <ScenarioBlock>
      <Position>
        <X>1727.828</X>
        <Y>2439.606</Y>
        <Z>44.56514</Z>
      </Position>
      <Distance>2</Distance>
      <DebugName>PrisonGeneral</DebugName>
    </ScenarioBlock>
    <ScenarioBlock>
      <Position>
        <X>1885.322</X>
        <Y>2626.629</Y>
        <Z>44.6721</Z>
      </Position>
      <Distance>2</Distance>
      <DebugName>PrisonGeneral</DebugName>
    </ScenarioBlock>
    <ScenarioBlock>
      <Position>
        <X>1846.473</X>
        <Y>2584.199</Y>
        <Z>44.67195</Z>
      </Position>
      <Distance>2</Distance>
      <DebugName>PrisonGeneral</DebugName>
    </ScenarioBlock>
    <ScenarioBlock>
      <Position>
        <X>1848.088</X>
        <Y>2602.314</Y>
        <Z>44.63724</Z>
      </Position>
      <Distance>2</Distance>
      <DebugName>PrisonGeneral</DebugName>
    </ScenarioBlock>
    <ScenarioBlock>
      <Position>
        <X>1848.083</X>
        <Y>2601.134</Y>
        <Z>44.62651</Z>
      </Position>
      <Distance>2</Distance>
      <DebugName>PrisonGeneral</DebugName>
    </ScenarioBlock>
    <ScenarioBlock>
      <Position>
        <X>1847.456</X>
        <Y>2603.807</Y>
        <Z>44.65017</Z>
      </Position>
      <Distance>2</Distance>
      <DebugName>PrisonGeneral</DebugName>
    </ScenarioBlock>
    <ScenarioBlock>
      <Position>
        <X>1955.374</X>
        <Y>2622.803</Y>
        <Z>44.90855</Z>
      </Position>
      <Distance>2</Distance>
      <DebugName>PrisonGeneral</DebugName>
    </ScenarioBlock>
    <ScenarioBlock>
      <Position>
        <X>1787.849</X>
        <Y>2622.388</Y>
        <Z>44.56556</Z>
      </Position>
      <Distance>2</Distance>
      <DebugName>PrisonGeneral</DebugName>
    </ScenarioBlock>
    <ScenarioBlock>
      <Position>
        <X>1774.152</X>
        <Y>2532.529</Y>
        <Z>44.56549</Z>
      </Position>
      <Distance>2</Distance>
      <DebugName>PrisonGeneral</DebugName>
    </ScenarioBlock>
    <ScenarioBlock>
      <Position>
        <X>1899.234</X>
        <Y>2605.696</Y>
        <Z>44.96621</Z>
      </Position>
      <Distance>2</Distance>
      <DebugName>PrisonGeneral</DebugName>
    </ScenarioBlock>
    <ScenarioBlock>
      <Position>
        <X>1847.575</X>
        <Y>2584.629</Y>
        <Z>45.67206</Z>
      </Position>
      <Distance>2</Distance>
      <DebugName>PrisonGeneral</DebugName>
    </ScenarioBlock>
    <ScenarioBlock>
      <Position>
        <X>1846.473</X>
        <Y>2584.199</Y>
        <Z>44.67195</Z>
      </Position>
      <Distance>2</Distance>
      <DebugName>PrisonGeneral</DebugName>
    </ScenarioBlock>
    <ScenarioBlock>
      <Position>
        <X>1847.933</X>
        <Y>2584.933</Y>
        <Z>44.67241</Z>
      </Position>
      <Distance>2</Distance>
      <DebugName>PrisonGeneral</DebugName>
    </ScenarioBlock>
    <ScenarioBlock>
      <Position>
        <X>1845.851</X>
        <Y>2587.203</Y>
        <Z>44.67231</Z>
      </Position>
      <Distance>2</Distance>
      <DebugName>PrisonGeneral</DebugName>
    </ScenarioBlock>
    <ScenarioBlock>
      <Position>
        <X>1850.889</X>
        <Y>2584.074</Y>
        <Z>44.67213</Z>
      </Position>
      <Distance>2</Distance>
      <DebugName>PrisonGeneral</DebugName>
    </ScenarioBlock>
    <ScenarioBlock>
      <Position>
        <X>1851.738</X>
        <Y>2598.987</Y>
        <Z>44.67213</Z>
      </Position>
      <Distance>2</Distance>
      <DebugName>PrisonGeneral</DebugName>
    </ScenarioBlock>
    <ScenarioBlock>
      <Position>
        <X>1850.146</X>
        <Y>2599.688</Y>
        <Z>44.648</Z>
      </Position>
      <Distance>2</Distance>
      <DebugName>PrisonGeneral</DebugName>
    </ScenarioBlock>
    <ScenarioBlock>
      <Position>
        <X>1848.083</X>
        <Y>2601.134</Y>
        <Z>44.62651</Z>
      </Position>
      <Distance>2</Distance>
      <DebugName>PrisonGeneral</DebugName>
    </ScenarioBlock>
    <ScenarioBlock>
      <Position>
        <X>1848.088</X>
        <Y>2602.314</Y>
        <Z>44.63724</Z>
      </Position>
      <Distance>2</Distance>
      <DebugName>PrisonGeneral</DebugName>
    </ScenarioBlock>
    <ScenarioBlock>
      <Position>
        <X>1847.456</X>
        <Y>2603.807</Y>
        <Z>44.65017</Z>
      </Position>
      <Distance>2</Distance>
      <DebugName>PrisonGeneral</DebugName>
    </ScenarioBlock>
    <ScenarioBlock>
      <Position>
        <X>1850.018</X>
        <Y>2603.395</Y>
        <Z>44.64648</Z>
      </Position>
      <Distance>2</Distance>
      <DebugName>PrisonGeneral</DebugName>
    </ScenarioBlock>
    <ScenarioBlock>
      <Position>
        <X>1852.137</X>
        <Y>2616.886</Y>
        <Z>44.67213</Z>
      </Position>
      <Distance>2</Distance>
      <DebugName>PrisonGeneral</DebugName>
    </ScenarioBlock>
    <ScenarioBlock>
      <Position>
        <X>1955.374</X>
        <Y>2622.803</Y>
        <Z>44.90855</Z>
      </Position>
      <Distance>2</Distance>
      <DebugName>PrisonGeneral</DebugName>
    </ScenarioBlock>
    <ScenarioBlock>
      <Position>
        <X>1899.234</X>
        <Y>2605.696</Y>
        <Z>44.96621</Z>
      </Position>
      <Distance>2</Distance>
      <DebugName>PrisonGeneral</DebugName>
    </ScenarioBlock>
    <ScenarioBlock>
      <Position>
        <X>1830.171</X>
        <Y>2602.584</Y>
        <Z>44.88912</Z>
      </Position>
      <Distance>2</Distance>
      <DebugName>PrisonGeneral</DebugName>
    </ScenarioBlock>
    <ScenarioBlock>
      <Position>
        <X>1815.909</X>
        <Y>2604.376</Y>
        <Z>44.65796</Z>
      </Position>
      <Distance>2</Distance>
      <DebugName>PrisonGeneral</DebugName>
    </ScenarioBlock>
    <ScenarioBlock>
      <Position>
        <X>1814.352</X>
        <Y>2604.741</Y>
        <Z>44.66116</Z>
      </Position>
      <Distance>2</Distance>
      <DebugName>PrisonGeneral</DebugName>
    </ScenarioBlock>
    <ScenarioBlock>
      <Position>
        <X>1813.006</X>
        <Y>2605.019</Y>
        <Z>44.66391</Z>
      </Position>
      <Distance>2</Distance>
      <DebugName>PrisonGeneral</DebugName>
    </ScenarioBlock>
    <ScenarioBlock>
      <Position>
        <X>1787.849</X>
        <Y>2622.388</Y>
        <Z>44.56556</Z>
      </Position>
      <Distance>2</Distance>
      <DebugName>PrisonGeneral</DebugName>
    </ScenarioBlock>
    <ScenarioBlock>
      <Position>
        <X>1751.283</X>
        <Y>2563.569</Y>
        <Z>54.44793</Z>
      </Position>
      <Distance>2</Distance>
      <DebugName>PrisonGeneral</DebugName>
    </ScenarioBlock>
    <ScenarioBlock>
      <Position>
        <X>1737.642</X>
        <Y>2561.494</Y>
        <Z>54.43274</Z>
      </Position>
      <Distance>2</Distance>
      <DebugName>PrisonGeneral</DebugName>
    </ScenarioBlock>
    <ScenarioBlock>
      <Position>
        <X>1737.16</X>
        <Y>2562.172</Y>
        <Z>54.43274</Z>
      </Position>
      <Distance>2</Distance>
      <DebugName>PrisonGeneral</DebugName>
    </ScenarioBlock>
    <ScenarioBlock>
      <Position>
        <X>1751.283</X>
        <Y>2563.569</Y>
        <Z>54.44793</Z>
      </Position>
      <Distance>2</Distance>
      <DebugName>PrisonGeneral</DebugName>
    </ScenarioBlock>
    <ScenarioBlock>
      <Position>
        <X>1733.784</X>
        <Y>2563.54</Y>
        <Z>54.44675</Z>
      </Position>
      <Distance>2</Distance>
      <DebugName>PrisonGeneral</DebugName>
    </ScenarioBlock>
    <ScenarioBlock>
      <Position>
        <X>1722.093</X>
        <Y>2563.476</Y>
        <Z>54.44793</Z>
      </Position>
      <Distance>2</Distance>
      <DebugName>PrisonGeneral</DebugName>
    </ScenarioBlock>
    <ScenarioBlock>
      <Position>
        <X>1701.468</X>
        <Y>2564.186</Y>
        <Z>54.43274</Z>
      </Position>
      <Distance>2</Distance>
      <DebugName>PrisonGeneral</DebugName>
    </ScenarioBlock>
    <ScenarioBlock>
      <Position>
        <X>1674.055</X>
        <Y>2564.076</Y>
        <Z>54.4313</Z>
      </Position>
      <Distance>2</Distance>
      <DebugName>PrisonGeneral</DebugName>
    </ScenarioBlock>
    <ScenarioBlock>
      <Position>
        <X>1662.51</X>
        <Y>2568.876</Y>
        <Z>54.44578</Z>
      </Position>
      <Distance>2</Distance>
      <DebugName>PrisonGeneral</DebugName>
    </ScenarioBlock>
    <ScenarioBlock>
      <Position>
        <X>1611.629</X>
        <Y>2570.046</Y>
        <Z>54.43207</Z>
      </Position>
      <Distance>2</Distance>
      <DebugName>PrisonGeneral</DebugName>
    </ScenarioBlock>
    <ScenarioBlock>
      <Position>
        <X>1606.765</X>
        <Y>2543.014</Y>
        <Z>54.43266</Z>
      </Position>
      <Distance>2</Distance>
      <DebugName>PrisonGeneral</DebugName>
    </ScenarioBlock>
    <ScenarioBlock>
      <Position>
        <X>1611.519</X>
        <Y>2537.367</Y>
        <Z>54.43208</Z>
      </Position>
      <Distance>2</Distance>
      <DebugName>PrisonGeneral</DebugName>
    </ScenarioBlock>
    <ScenarioBlock>
      <Position>
        <X>1621.769</X>
        <Y>2511.902</Y>
        <Z>54.38113</Z>
      </Position>
      <Distance>2</Distance>
      <DebugName>PrisonGeneral</DebugName>
    </ScenarioBlock>
    <ScenarioBlock>
      <Position>
        <X>1621.278</X>
        <Y>2511.366</Y>
        <Z>54.43208</Z>
      </Position>
      <Distance>2</Distance>
      <DebugName>PrisonGeneral</DebugName>
    </ScenarioBlock>
    <ScenarioBlock>
      <Position>
        <X>1639.437</X>
        <Y>2490.519</Y>
        <Z>54.40924</Z>
      </Position>
      <Distance>2</Distance>
      <DebugName>PrisonGeneral</DebugName>
    </ScenarioBlock>
    <ScenarioBlock>
      <Position>
        <X>1646.959</X>
        <Y>2490.754</Y>
        <Z>54.43208</Z>
      </Position>
      <Distance>2</Distance>
      <DebugName>PrisonGeneral</DebugName>
    </ScenarioBlock>
    <ScenarioBlock>
      <Position>
        <X>1676.462</X>
        <Y>2482.589</Y>
        <Z>54.40998</Z>
      </Position>
      <Distance>2</Distance>
      <DebugName>PrisonGeneral</DebugName>
    </ScenarioBlock>
    <ScenarioBlock>
      <Position>
        <X>1703.719</X>
        <Y>2477.959</Y>
        <Z>54.3774</Z>
      </Position>
      <Distance>2</Distance>
      <DebugName>PrisonGeneral</DebugName>
    </ScenarioBlock>
    <ScenarioBlock>
      <Position>
        <X>1709.409</X>
        <Y>2482.831</Y>
        <Z>54.40908</Z>
      </Position>
      <Distance>2</Distance>
      <DebugName>PrisonGeneral</DebugName>
    </ScenarioBlock>
    <ScenarioBlock>
      <Position>
        <X>1733.246</X>
        <Y>2505.29</Y>
        <Z>54.39078</Z>
      </Position>
      <Distance>2</Distance>
      <DebugName>PrisonGeneral</DebugName>
    </ScenarioBlock>
    <ScenarioBlock>
      <Position>
        <X>1740.667</X>
        <Y>2504.186</Y>
        <Z>54.35909</Z>
      </Position>
      <Distance>2</Distance>
      <DebugName>PrisonGeneral</DebugName>
    </ScenarioBlock>
    <ScenarioBlock>
      <Position>
        <X>1759.357</X>
        <Y>2514.872</Y>
        <Z>54.3591</Z>
      </Position>
      <Distance>2</Distance>
      <DebugName>PrisonGeneral</DebugName>
    </ScenarioBlock>
    <ScenarioBlock>
      <Position>
        <X>1761.915</X>
        <Y>2521.84</Y>
        <Z>54.39047</Z>
      </Position>
      <Distance>2</Distance>
      <DebugName>PrisonGeneral</DebugName>
    </ScenarioBlock>
    <ScenarioBlock>
      <Position>
        <X>-755.6989</X>
        <Y>-920.1201</Y>
        <Z>19.07203</Z>
      </Position>
      <Distance>10</Distance>
      <DebugName>KoreanSteps</DebugName>
    </ScenarioBlock>
    <ScenarioBlock>
      <Position>
        <X>-762.5551</X>
        <Y>-919.5652</Y>
        <Z>20.15879</Z>
      </Position>
      <Distance>10</Distance>
      <DebugName>KoreanSteps</DebugName>
    </ScenarioBlock>
    <ScenarioBlock>
      <Position>
        <X>-764.7227</X>
        <Y>-917.3176</Y>
        <Z>20.80979</Z>
      </Position>
      <Distance>10</Distance>
      <DebugName>KoreanSteps</DebugName>
    </ScenarioBlock>
    <ScenarioBlock>
      <Position>
        <X>-764.3928</X>
        <Y>-923.0778</Y>
        <Z>18.72722</Z>
      </Position>
      <Distance>10</Distance>
      <DebugName>KoreanSteps</DebugName>
    </ScenarioBlock>
    <ScenarioBlock>
      <Position>
        <X>-763.5527</X>
        <Y>-932.0254</Y>
        <Z>18.14868</Z>
      </Position>
      <Distance>10</Distance>
      <DebugName>KoreanSteps</DebugName>
    </ScenarioBlock>
    <ScenarioBlock>
      <Position>
        <X>1382.979</X>
        <Y>1147.941</Y>
        <Z>113.3342</Z>
      </Position>
      <Distance>10</Distance>
      <DebugName>VagosCartel</DebugName>
    </ScenarioBlock>
    <ScenarioBlock>
      <Position>
        <X>1382.747</X>
        <Y>1146.689</Y>
        <Z>113.3342</Z>
      </Position>
      <Distance>10</Distance>
      <DebugName>VagosCartel</DebugName>
    </ScenarioBlock>
    <ScenarioBlock>
      <Position>
        <X>1392.486</X>
        <Y>1154.698</Y>
        <Z>113.4431</Z>
      </Position>
      <Distance>10</Distance>
      <DebugName>VagosCartel</DebugName>
    </ScenarioBlock>
    <ScenarioBlock>
      <Position>
        <X>1392.104</X>
        <Y>1155.521</Y>
        <Z>113.4431</Z>
      </Position>
      <Distance>10</Distance>
      <DebugName>VagosCartel</DebugName>
    </ScenarioBlock>
    <ScenarioBlock>
      <Position>
        <X>1391.452</X>
        <Y>1157.046</Y>
        <Z>113.4431</Z>
      </Position>
      <Distance>10</Distance>
      <DebugName>VagosCartel</DebugName>
    </ScenarioBlock>
    <ScenarioBlock>
      <Position>
        <X>1390.901</X>
        <Y>1157.986</Y>
        <Z>113.4431</Z>
      </Position>
      <Distance>10</Distance>
      <DebugName>VagosCartel</DebugName>
    </ScenarioBlock>
    <ScenarioBlock>
      <Position>
        <X>1387.192</X>
        <Y>1158.324</Y>
        <Z>113.3342</Z>
      </Position>
      <Distance>10</Distance>
      <DebugName>VagosCartel</DebugName>
    </ScenarioBlock>
    <ScenarioBlock>
      <Position>
        <X>1413.152</X>
        <Y>1153.463</Y>
        <Z>113.3341</Z>
      </Position>
      <Distance>10</Distance>
      <DebugName>VagosCartel</DebugName>
    </ScenarioBlock>
    <ScenarioBlock>
      <Position>
        <X>1419.978</X>
        <Y>1151.363</Y>
        <Z>113.6739</Z>
      </Position>
      <Distance>10</Distance>
      <DebugName>VagosCartel</DebugName>
    </ScenarioBlock>
    <ScenarioBlock>
      <Position>
        <X>1416.658</X>
        <Y>1163.833</Y>
        <Z>114.3532</Z>
      </Position>
      <Distance>10</Distance>
      <DebugName>VagosCartel</DebugName>
    </ScenarioBlock>
  </ScenarioBlocks>
</PossibleSpawnBlocks>